{
    "atualizado_em": "30/05/2026 13:03",
    "total_posts": 339,
    "total_mes_atual": 167,
    "ranking": {
        "Itapetinga": 35,
        "Xique_Xique": 34,
        "Uruçuca": 31,
        "Guanambi": 29,
        "Teixeira_de_Freitas": 27,
        "Santa_Inês": 25,
        "Bom_Jesus_da_Lapa": 25,
        "Alagoinhas": 24,
        "Catu": 24,
        "Itaberaba": 24,
        "Valença": 19,
        "Serrinha": 17,
        "Governador_Mangabeira": 14,
        "Reitoria": 10,
        "Senhor_do_Bonfim": 1
    },
    "ritmo_publicacao": {
        "2026-05-01": 4,
        "2026-05-02": 4,
        "2026-05-03": 1,
        "2026-05-04": 2,
        "2026-05-05": 1,
        "2026-05-06": 2,
        "2026-05-07": 4,
        "2026-05-08": 4,
        "2026-05-09": 1,
        "2026-05-10": 3,
        "2026-05-11": 2,
        "2026-05-12": 1,
        "2026-05-13": 10,
        "2026-05-14": 8,
        "2026-05-15": 12,
        "2026-05-16": 13,
        "2026-05-17": 9,
        "2026-05-18": 4,
        "2026-05-19": 7,
        "2026-05-20": 11,
        "2026-05-21": 9,
        "2026-05-22": 7,
        "2026-05-23": 4,
        "2026-05-24": 3,
        "2026-05-25": 7,
        "2026-05-26": 3,
        "2026-05-27": 11,
        "2026-05-28": 6,
        "2026-05-29": 5,
        "2026-05-30": 6
    },
    "mensal": {
        "2025-05": 3,
        "2025-06": 2,
        "2025-07": 4,
        "2025-08": 9,
        "2025-09": 10,
        "2025-10": 9,
        "2025-11": 12,
        "2025-12": 8,
        "2026-01": 12,
        "2026-02": 14,
        "2026-03": 23,
        "2026-04": 69,
        "2026-05": 164
    },
    "dias_produtivos": {
        "2": 71,
        "3": 58,
        "4": 56,
        "5": 46,
        "1": 46,
        "0": 40,
        "6": 22
    },
    "inatividade": {
        "Reitoria": 3,
        "Alagoinhas": 4,
        "Bom_Jesus_da_Lapa": 4,
        "Catu": 2,
        "Governador_Mangabeira": 0,
        "Guanambi": 2,
        "Itaberaba": 0,
        "Itapetinga": 1,
        "Santa_Inês": 0,
        "Senhor_do_Bonfim": 5,
        "Serrinha": 8,
        "Teixeira_de_Freitas": 1,
        "Uruçuca": 1,
        "Valença": 1,
        "Xique_Xique": 0
    },
    "dia_mais_produtivo": "Quarta"
}